pyuac/__init__.py
pyuac/__version__.py
pyuac/admin.py
pyuac/decorator.py
pyuac/main_decorator.py
pyuac-0.0.3.dist-info/LICENSE
pyuac-0.0.3.dist-info/METADATA
pyuac-0.0.3.dist-info/WHEEL
pyuac-0.0.3.dist-info/top_level.txt
pyuac-0.0.3.dist-info/RECORD
