Metadata-Version: 2.1
Name: pyuac
Version: 0.0.3
Summary: Python library for Windows User Access Control (UAC)
Home-page: https://github.com/Preston-Landers/pyuac
Author: Preston Landers
Author-email: planders@utexas.edu
License: MIT
Project-URL: Source, https://github.com/Preston-Landers/pyuac
Platform: UNKNOWN
Classifier: Programming Language :: Python :: 3
Classifier: Programming Language :: Python :: 2.7
Classifier: License :: OSI Approved :: MIT License
Classifier: Operating System :: Microsoft :: Windows
Classifier: Development Status :: 4 - Beta
Classifier: Environment :: Console
Classifier: Environment :: Win32 (MS Windows)
Classifier: Intended Audience :: Developers
Requires-Python: >=2.7, !=3.0.*, !=3.1.*, !=3.2.*
